pyromod/__init__.py
pyromod/filters/__init__.py
pyromod/filters/filters.py
pyromod/helpers/__init__.py
pyromod/helpers/helpers.py
pyromod/listen/__init__.py
pyromod/listen/listen.py
pyromod/nav/__init__.py
pyromod/nav/pagination.py
pyromod/utils/__init__.py
pyromod/utils/utils.py
pyromodded-1.5.dist-info/COPYING
pyromodded-1.5.dist-info/COPYING.lesser
pyromodded-1.5.dist-info/METADATA
pyromodded-1.5.dist-info/NOTICE
pyromodded-1.5.dist-info/WHEEL
pyromodded-1.5.dist-info/top_level.txt
pyromodded-1.5.dist-info/RECORD
